te2_sdk/__init__.py
te2_sdk/te2.py
te2_sdk-0.1.5.dist-info/DESCRIPTION.rst
te2_sdk-0.1.5.dist-info/METADATA
te2_sdk-0.1.5.dist-info/RECORD
te2_sdk-0.1.5.dist-info/WHEEL
te2_sdk-0.1.5.dist-info/metadata.json
te2_sdk-0.1.5.dist-info/top_level.txt
