Metadata-Version: 2.0
Name: te2-sdk
Version: 0.1.5
Summary: Simple Wrapper for Terraform Enterprise 2 Jobs
Home-page: https://github.com/westpac-cloud-engineering/Terraform-Enterprise-2-Python-SDK
Author: Rory Chatterton
Author-email: rchatterton@westpac.com.au
License: MIT License
Requires-Dist: requests
Provides-Extra: test
Requires-Dist: coverage; extra == 'test'
Requires-Dist: pytest; extra == 'test'
Requires-Dist: pytest-cov; extra == 'test'
